pysait
