Metadata-Version: 1.1
Name: PySait
Version: 1.3
Summary: Site; compact, fast.
Home-page: https://bitbucket.org/creeerio/pysait
Author: Nils
Author-email: nils@creeer.io
License: MIT
Platform: UNKNOWN
Classifier: Development Status :: 3 - Alpha
Classifier: Intended Audience :: Developers
Classifier: License :: OSI Approved :: MIT License
Classifier: Programming Language :: Python :: 3.5
